ltep_athena_api/__init__.py
ltep_athena_api/athena_api.py
ltep_athena_api/authenticate.py
ltep_athena_api/constants.py
ltep_athena_api/deploy.py
ltep_athena_api/microservice.py
ltep_athena_api/models/AnalysisBlock.py
ltep_athena_api/models/Cleanser.py
ltep_athena_api/models/CleanserResult.py
ltep_athena_api/models/CustomHTMLDocument.py
ltep_athena_api/models/CustomOperation.py
ltep_athena_api/models/DataSet.py
ltep_athena_api/models/InputForm.py
ltep_athena_api/models/WorkflowOperation.py
ltep_athena_api/models/__init__.py
ltep_athena_api/tests/__init__.py
ltep_athena_api/tests/conftest.py
ltep_athena_api/tests/e2e/__init__.py
ltep_athena_api/tests/integration/__init__.py
ltep_athena_api/tests/integration/test_custom_html_document.py
ltep_athena_api/tests/unit/__init__.py
ltep_athena_api/tests/unit/test_chart_formatting.py
ltep_athena_api-1.0.0.dist-info/LICENSE
ltep_athena_api-1.0.0.dist-info/METADATA
ltep_athena_api-1.0.0.dist-info/WHEEL
ltep_athena_api-1.0.0.dist-info/top_level.txt
ltep_athena_api-1.0.0.dist-info/RECORD
