Metadata-Version: 2.1
Name: ltep-athena-api
Version: 1.0.0
Summary: The official LTEP Athena API: Welcome to the World's most flexible and extensible Data Science and Automation Platform
Home-page: https://github.com/efstratios97/ltep_athena_api
Author: Efstratios Pahis from LTEP Technologies
License: MIT
Classifier: Programming Language :: Python :: 3
Classifier: License :: OSI Approved :: MIT License
Classifier: Operating System :: OS Independent
Requires-Python: >=3.7
License-File: LICENSE
Requires-Dist: attrs ==22.1.0
Requires-Dist: autopep8 ==2.0.0
Requires-Dist: bidict ==0.22.0
Requires-Dist: certifi ==2022.9.24
Requires-Dist: cffi ==1.15.1
Requires-Dist: charset-normalizer ==2.1.1
Requires-Dist: click ==8.1.3
Requires-Dist: colorama ==0.4.6
Requires-Dist: Deprecated ==1.2.13
Requires-Dist: Flask ==2.2.2
Requires-Dist: Flask-Cors ==3.0.10
Requires-Dist: gevent ==22.10.2
Requires-Dist: greenlet ==2.0.1
Requires-Dist: idna ==3.4
Requires-Dist: iniconfig ==1.1.1
Requires-Dist: itsdangerous ==2.1.2
Requires-Dist: Jinja2 ==3.1.2
Requires-Dist: MarkupSafe ==2.1.1
Requires-Dist: multi-key-dict ==2.0.3
Requires-Dist: numpy ==1.23.4
Requires-Dist: packaging ==21.3
Requires-Dist: pandas ==1.5.1
Requires-Dist: pbr ==5.11.0
Requires-Dist: pluggy ==1.0.0
Requires-Dist: pycodestyle ==2.9.1
Requires-Dist: pycparser ==2.21
Requires-Dist: PyGithub ==1.57
Requires-Dist: PyJWT ==2.6.0
Requires-Dist: PyNaCl ==1.5.0
Requires-Dist: pyparsing ==3.0.9
Requires-Dist: python-dateutil ==2.8.2
Requires-Dist: python-engineio ==4.3.4
Requires-Dist: python-jenkins ==1.7.0
Requires-Dist: python-socketio ==5.7.2
Requires-Dist: pytz ==2022.6
Requires-Dist: PyYAML ==6.0
Requires-Dist: Random-Word ==1.0.11
Requires-Dist: randomword ==1.0.2
Requires-Dist: requests ==2.28.1
Requires-Dist: six ==1.16.0
Requires-Dist: tomli ==2.0.1
Requires-Dist: urllib3 ==1.26.12
Requires-Dist: websocket-client ==1.4.2
Requires-Dist: Werkzeug ==2.2.2
Requires-Dist: wrapt ==1.14.1
Requires-Dist: zope.event ==4.5.0
Requires-Dist: zope.interface ==5.5.1
